Workbook

Sheet Summary
A1: Pipeline Dashboard - Summary
A3: Metric | B3: Value
A4: ── ACTIVE PIPELINE ──
A5: Open Deals | B5: 67
A6: Total Pipeline (Balance) | B6: 2.311264e+08
A7: Weighted Pipeline | B7: 81034584
A8: Total Revenue Potential | B8: 7960448.6
A9: Weighted Revenue | B9: 3037576.4
A11: ── CLOSED YTD ──
A12: Closed Deals | B12: 9
A13: Closed Revenue (YTD) | B13: 325470.72
A15: ── STAGE BREAKDOWN ──
A16: Lead | B16: 25
A17: Qualified | B17: 18
A18: Proposal | B18: 15
A19: Commit | B19: 9
A20: Closed | B20: 9

Sheet Active Pipeline
A1: Deal ID | B1: Officer ID | C1: Officer Name | D1: Market | E1: Customer | F1: Product | G1: Stage | H1: Amount | I1: Probability | J1: Days in Stage | K1: Age (Days) | L1: Expected Close | M1: Annual Revenue
A2: h-reyes-0 | B2: h-reyes | C2: M. Reyes | D2: Houston | E2: Northstar Tech | F2: Deposits | G2: Qualified | H2: 1986780.8 | I2: 0.29663447 | J2: 45 | K2: 84 | L2: 46331 | M2: 9933.9038
A3: h-reyes-2 | B3: h-reyes | C3: M. Reyes | D3: Houston | E3: Pacific Imports | F3: Treasury Management | G3: Proposal | H3: 204686.79 | I3: 0.50041637 | J3: 65 | K3: 155 | L3: 46280 | M3: 204686.79
A4: h-reyes-4 | B4: h-reyes | C4: M. Reyes | D4: Houston | E4: Redwood Construction | F4: Deposits | G4: Qualified | H4: 2490783.8 | I4: 0.23336698 | J4: 75 | K4: 121 | L4: 46351 | M4: 12453.919
A5: h-reyes-5 | B5: h-reyes | C5: M. Reyes | D5: Houston | E5: Summit Hospitality | F5: Other Fees | G5: Qualified | H5: 56309.168 | I5: 0.21516522 | J5: 53 | K5: 97 | L5: 46311 | M5: 56309.168
A6: h-reyes-6 | B6: h-reyes | C6: M. Reyes | D6: Houston | E6: Trinity Pharma | F6: Other Fees | G6: Lead | H6: 36726.205 | I6: 0.065733885 | J6: 51 | K6: 79 | L6: 46330 | M6: 36726.205
A7: h-reyes-7 | B7: h-reyes | C7: M. Reyes | D7: Houston | E7: Union Distributors | F7: Commercial Loan | G7: Qualified | H7: 1681430.4 | I7: 0.22000934 | J7: 88 | K7: 145 | L7: 46332 | M7: 57168.634
A8: h-reyes-8 | B8: h-reyes | C8: M. Reyes | D8: Houston | E8: Vanguard Plastics | F8: Deposits | G8: Commit | H8: 1591906.9 | I8: 0.79768678 | J8: 47 | K8: 165 | L8: 46263 | M8: 7959.5346
A9: h-reyes-9 | B9: h-reyes | C9: M. Reyes | D9: Houston | E9: Westfield Retail | F9: Deposits | G9: Lead | H9: 5644082.3 | I9: 0.090537016 | J9: 38 | K9: 55 | L9: 46380 | M9: 28220.412
A10: h-reyes-10 | B10: h-reyes | C10: M. Reyes | D10: Houston | E10: Yellowstone Ranch | F10: Commercial Loan | G10: Lead | H10: 2214860.6 | I10: 0.12286659 | J10: 45 | K10: 67 | L10: 46358 | M10: 75305.26
A11: h-reyes-11 | B11: h-reyes | C11: M. Reyes | D11: Houston | E11: Zenith Software | F11: Deposits | G11: Lead | H11: 631615.27 | I11: 0.1411697 | J11: 24 | K11: 31 | L11: 46364 | M11: 3158.0764
A12: h-reyes-13 | B12: h-reyes | C12: M. Reyes | D12: Houston | E12: Brazos Petroleum | F12: Treasury Management | G12: Proposal | H12: 258735.19 | I12: 0.48768675 | J12: 17 | K12: 98 | L12: 46264 | M12: 258735.19
A13: h-patel-0 | B13: h-patel | C13: D. Patel | D13: Houston | E13: Zenith Software | F13: Deposits | G13: Lead | H13: 3805889.5 | I13: 0.146238 | J13: 88 | K13: 89 | L13: 46383 | M13: 19029.447
... A68: d-foster-12 | B68: d-foster | C68: B. Foster | D68: Dallas | E68: Zenith Software | F68: Commercial Loan | G68: Commit | H68: 9360282.9 | I68: 0.75103694 | J68: 43 | K68: 139 | L68: 46247 | M68: 318249.62

Sheet Closed YTD
A1: Deal ID | B1: Officer ID | C1: Officer Name | D1: Market | E1: Customer | F1: Product | G1: Stage | H1: Amount | I1: Probability | J1: Days in Stage | K1: Age (Days) | L1: Close Date | M1: Annual Revenue
A2: h-reyes-1 | B2: h-reyes | C2: M. Reyes | D2: Houston | E2: Oakridge Auto | F2: Treasury Management | G2: Closed | H2: 56255.376 | I2: 1 | J2: 58 | K2: 203 | L2: 46210 | M2: 56255.376
A3: h-reyes-3 | B3: h-reyes | C3: M. Reyes | D3: Houston | E3: Quartz Mining | F3: Deposits | G3: Closed | H3: 779213.01 | I3: 1 | J3: 16 | K3: 160 | L3: 46231 | M3: 3896.0651
A4: h-reyes-12 | B4: h-reyes | C4: M. Reyes | D4: Houston | E4: Alamo Equipment | F4: Commercial Loan | G4: Closed | H4: 815121.37 | I4: 1 | J4: 37 | K4: 185 | L4: 46242 | M4: 27714.127
A5: h-patel-8 | B5: h-patel | C5: D. Patel | D5: Houston | E5: Delta Manufacturing | F5: Commercial Loan | G5: Closed | H5: 670519.57 | I5: 1 | J5: 11 | K5: 148 | L5: 46216 | M5: 22797.665
A6: h-patel-13 | B6: h-patel | C6: D. Patel | D6: Houston | E6: Juniper Foods | F6: Commercial Loan | G6: Closed | H6: 1212020.7 | I6: 1 | J6: 34 | K6: 154 | L6: 46229 | M6: 41208.705
A7: h-tran-7 | B7: h-tran | C7: A. Tran | D7: Houston | E7: Fairfield Energy | F7: Deposits | G7: Closed | H7: 713863.45 | I7: 1 | J7: 39 | K7: 168 | L7: 46228 | M7: 3569.3172
A8: d-garcia-2 | B8: d-garcia | C8: S. Garcia | D8: Dallas | E8: Westfield Retail | F8: Commercial Loan | G8: Closed | H8: 3693911.7 | I8: 1 | J8: 105 | K8: 231 | L8: 46213 | M8: 125593
A9: d-foster-7 | B9: d-foster | C9: B. Foster | D9: Dallas | E9: Lakeside Medical | F9: Treasury Management | G9: Closed | H9: 36610.28 | I9: 1 | J9: 14 | K9: 138 | L9: 46240 | M9: 36610.28
A10: d-foster-13 | B10: d-foster | C10: B. Foster | D10: Dallas | E10: Alamo Equipment | F10: Deposits | G10: Closed | H10: 1565237.5 | I10: 1 | J10: 55 | K10: 195 | L10: 46224 | M10: 7826.1877

Sheet README
A1: RM Pipeline Template
A4: How to use | B4: Each RM has their own tab (named with your initial + last name). Fill in only your tab. Submit the workbook when ready and the dashboard will refresh.
A5: Tabs | B5: README · Summary (auto-calculated rollup) · one tab per RM. Lookup is hidden — leave it alone.
A7: Required | B7: Customer · Product · Stage · Amount · Date Entered Stage
A8: Auto-filled | B8: Probability (from Stage), Days in Stage (from date), Annual Rev (from Product+Amount), Weighted Rev (Annual × Probability). Cells with these formulas are light blue.
A9: Overriding | B9: Probability auto-fills from Stage, but you can type a number over the formula if your judgment differs.
A11: Products | B11: Comm Loan · Deposits · Treasury Mgmt · Other Fees
A12: Stages (prob) | B12: Lead (10%) · Qualified (25%) · Proposal (50%) · Commit (80%) · Closed (100%)
A14: Amount units | B14: Comm Loan / Deposits = loan or deposit balance in dollars. Treasury Mgmt / Other Fees = annual fee revenue in dollars.
A15: Annual rev | B15: For loans/deposits, Annual Rev = Amount × spread (3.4% commercial loan, 0.5% deposit). For TM/Other, Annual Rev = Amount as entered.
A16: Closed deals | B16: Mark Stage = Closed when funded/booked. Closed deals count toward Closed YTD on the dashboard but are excluded from open pipeline.
A18: Aging colors | B18: Days in Stage > 90 highlight red; 61-90 amber. Use these to triage stuck deals.
A19: Notes column | B19: Free text. Use it for things the columns don't capture (credit conditions, RM commentary, blockers).

Sheet M. Reyes
A1: M. Reyes · Houston · Pipeline
A2: Customer | B2: Product | C2: Stage | D2: Amount ($) | E2: Probability | F2: Date Entered Stage | G2: Days in Stage | H2: Expected Close | I2: Annual Rev ($) | J2: Weighted Rev ($) | K2: Notes
A3: Northstar Tech | B3: Deposits | C3: Qualified | D3: 1986780.8 | E3: 0.2966 | F3: 46158 | G3: =IF(F3="","",TODAY()-F3) | H3: 46331 | I3: =IF(OR(B3="",D3=""),"",D3*VLOOKUP(B3,Lookup!$A$2:$B$5,2,FALSE)) | J3: =IF(OR(I3="",E3=""),"",I3*E3)
A4: Oakridge Auto | B4: Treasury Mgmt | C4: Closed | D4: 56255.38 | E4: 1 | F4: 46145 | G4: =IF(F4="","",TODAY()-F4) | H4: 46210 | I4: =IF(OR(B4="",D4=""),"",D4*VLOOKUP(B4,Lookup!$A$2:$B$5,2,FALSE)) | J4: =IF(OR(I4="",E4=""),"",I4*E4)
A5: Pacific Imports | B5: Treasury Mgmt | C5: Proposal | D5: 204686.79 | E5: 0.5004 | F5: 46138 | G5: =IF(F5="","",TODAY()-F5) | H5: 46280 | I5: =IF(OR(B5="",D5=""),"",D5*VLOOKUP(B5,Lookup!$A$2:$B$5,2,FALSE)) | J5: =IF(OR(I5="",E5=""),"",I5*E5)
A6: Quartz Mining | B6: Deposits | C6: Closed | D6: 779213.01 | E6: 0.974 | F6: 46187 | G6: =IF(F6="","",TODAY()-F6) | H6: 46231 | I6: =IF(OR(B6="",D6=""),"",D6*VLOOKUP(B6,Lookup!$A$2:$B$5,2,FALSE)) | J6: =IF(OR(I6="",E6=""),"",I6*E6)
A7: Redwood Construction | B7: Deposits | C7: Qualified | D7: 2490783.8 | E7: 0.2334 | F7: 46128 | G7: =IF(F7="","",TODAY()-F7) | H7: 46351 | I7: =IF(OR(B7="",D7=""),"",D7*VLOOKUP(B7,Lookup!$A$2:$B$5,2,FALSE)) | J7: =IF(OR(I7="",E7=""),"",I7*E7)
A8: Summit Hospitality | B8: Other Fees | C8: Qualified | D8: 56309.17 | E8: 0.2152 | F8: 46150 | G8: =IF(F8="","",TODAY()-F8) | H8: 46311 | I8: =IF(OR(B8="",D8=""),"",D8*VLOOKUP(B8,Lookup!$A$2:$B$5,2,FALSE)) | J8: =IF(OR(I8="",E8=""),"",I8*E8)
A9: Trinity Pharma | B9: Other Fees | C9: Lead | D9: 36726.21 | E9: 0.0657 | F9: 46152 | G9: =IF(F9="","",TODAY()-F9) | H9: 46330 | I9: =IF(OR(B9="",D9=""),"",D9*VLOOKUP(B9,Lookup!$A$2:$B$5,2,FALSE)) | J9: =IF(OR(I9="",E9=""),"",I9*E9)
A10: Union Distributors | B10: Comm Loan | C10: Qualified | D10: 1681430.4 | E10: 0.22 | F10: 46115 | G10: =IF(F10="","",TODAY()-F10) | H10: 46332 | I10: =IF(OR(B10="",D10=""),"",D10*VLOOKUP(B10,Lookup!$A$2:$B$5,2,FALSE)) | J10: =IF(OR(I10="",E10=""),"",I10*E10)
A11: Vanguard Plastics | B11: Deposits | C11: Commit | D11: 1591906.9 | E11: 0.7977 | F11: 46156 | G11: =IF(F11="","",TODAY()-F11) | H11: 46263 | I11: =IF(OR(B11="",D11=""),"",D11*VLOOKUP(B11,Lookup!$A$2:$B$5,2,FALSE)) | J11: =IF(OR(I11="",E11=""),"",I11*E11)
A12: Westfield Retail | B12: Deposits | C12: Lead | D12: 5644082.3 | E12: 0.0905 | F12: 46165 | G12: =IF(F12="","",TODAY()-F12) | H12: 46380 | I12: =IF(OR(B12="",D12=""),"",D12*VLOOKUP(B12,Lookup!$A$2:$B$5,2,FALSE)) | J12: =IF(OR(I12="",E12=""),"",I12*E12)
A13: Yellowstone Ranch | B13: Comm Loan | C13: Lead | D13: 2214860.6 | E13: 0.1229 | F13: 46158 | G13: =IF(F13="","",TODAY()-F13) | H13: 46358 | I13: =IF(OR(B13="",D13=""),"",D13*VLOOKUP(B13,Lookup!$A$2:$B$5,2,FALSE)) | J13: =IF(OR(I13="",E13=""),"",I13*E13)
A14: Zenith Software | B14: Deposits | C14: Lead | D14: 631615.27 | E14: 0.1412 | F14: 46179 | G14: =IF(F14="","",TODAY()-F14) | H14: 46364 | I14: =IF(OR(B14="",D14=""),"",D14*VLOOKUP(B14,Lookup!$A$2:$B$5,2,FALSE)) | J14: =IF(OR(I14="",E14=""),"",I14*E14)
... A16: Brazos Petroleum | B16: Treasury Mgmt | C16: Proposal | D16: 258735.19 | E16: 0.4877 | F16: 46186 | G16: =IF(F16="","",TODAY()-F16) | H16: 46264 | I16: =IF(OR(B16="",D16=""),"",D16*VLOOKUP(B16,Lookup!$A$2:$B$5,2,FALSE)) | J16: =IF(OR(I16="",E16=""),"",I16*E16)
E17: =IF(C17="","",VLOOKUP(C17,Lookup!$D$2:$E$6,2,FALSE)) | G17: =IF(F17="","",TODAY()-F17) | I17: =IF(OR(B17="",D17=""),"",D17*VLOOKUP(B17,Lookup!$A$2:$B$5,2,FALSE)) | J17: =IF(OR(I17="",E17=""),"",I17*E17)
E18: =IF(C18="","",VLOOKUP(C18,Lookup!$D$2:$E$6,2,FALSE)) | G18: =IF(F18="","",TODAY()-F18) | I18: =IF(OR(B18="",D18=""),"",D18*VLOOKUP(B18,Lookup!$A$2:$B$5,2,FALSE)) | J18: =IF(OR(I18="",E18=""),"",I18*E18)
E19: =IF(C19="","",VLOOKUP(C19,Lookup!$D$2:$E$6,2,FALSE)) | G19: =IF(F19="","",TODAY()-F19) | I19: =IF(OR(B19="",D19=""),"",D19*VLOOKUP(B19,Lookup!$A$2:$B$5,2,FALSE)) | J19: =IF(OR(I19="",E19=""),"",I19*E19)
E20: =IF(C20="","",VLOOKUP(C20,Lookup!$D$2:$E$6,2,FALSE)) | G20: =IF(F20="","",TODAY()-F20) | I20: =IF(OR(B20="",D20=""),"",D20*VLOOKUP(B20,Lookup!$A$2:$B$5,2,FALSE)) | J20: =IF(OR(I20="",E20=""),"",I20*E20)
E21: =IF(C21="","",VLOOKUP(C21,Lookup!$D$2:$E$6,2,FALSE)) | G21: =IF(F21="","",TODAY()-F21) | I21: =IF(OR(B21="",D21=""),"",D21*VLOOKUP(B21,Lookup!$A$2:$B$5,2,FALSE)) | J21: =IF(OR(I21="",E21=""),"",I21*E21)
E22: =IF(C22="","",VLOOKUP(C22,Lookup!$D$2:$E$6,2,FALSE)) | G22: =IF(F22="","",TODAY()-F22) | I22: =IF(OR(B22="",D22=""),"",D22*VLOOKUP(B22,Lookup!$A$2:$B$5,2,FALSE)) | J22: =IF(OR(I22="",E22=""),"",I22*E22)
E23: =IF(C23="","",VLOOKUP(C23,Lookup!$D$2:$E$6,2,FALSE)) | G23: =IF(F23="","",TODAY()-F23) | I23: =IF(OR(B23="",D23=""),"",D23*VLOOKUP(B23,Lookup!$A$2:$B$5,2,FALSE)) | J23: =IF(OR(I23="",E23=""),"",I23*E23)
E24: =IF(C24="","",VLOOKUP(C24,Lookup!$D$2:$E$6,2,FALSE)) | G24: =IF(F24="","",TODAY()-F24) | I24: =IF(OR(B24="",D24=""),"",D24*VLOOKUP(B24,Lookup!$A$2:$B$5,2,FALSE)) | J24: =IF(OR(I24="",E24=""),"",I24*E24)
E25: =IF(C25="","",VLOOKUP(C25,Lookup!$D$2:$E$6,2,FALSE)) | G25: =IF(F25="","",TODAY()-F25) | I25: =IF(OR(B25="",D25=""),"",D25*VLOOKUP(B25,Lookup!$A$2:$B$5,2,FALSE)) | J25: =IF(OR(I25="",E25=""),"",I25*E25)
E26: =IF(C26="","",VLOOKUP(C26,Lookup!$D$2:$E$6,2,FALSE)) | G26: =IF(F26="","",TODAY()-F26) | I26: =IF(OR(B26="",D26=""),"",D26*VLOOKUP(B26,Lookup!$A$2:$B$5,2,FALSE)) | J26: =IF(OR(I26="",E26=""),"",I26*E26)
E27: =IF(C27="","",VLOOKUP(C27,Lookup!$D$2:$E$6,2,FALSE)) | G27: =IF(F27="","",TODAY()-F27) | I27: =IF(OR(B27="",D27=""),"",D27*VLOOKUP(B27,Lookup!$A$2:$B$5,2,FALSE)) | J27: =IF(OR(I27="",E27=""),"",I27*E27)
E28: =IF(C28="","",VLOOKUP(C28,Lookup!$D$2:$E$6,2,FALSE)) | G28: =IF(F28="","",TODAY()-F28) | I28: =IF(OR(B28="",D28=""),"",D28*VLOOKUP(B28,Lookup!$A$2:$B$5,2,FALSE)) | J28: =IF(OR(I28="",E28=""),"",I28*E28)
... E32: =IF(C32="","",VLOOKUP(C32,Lookup!$D$2:$E$6,2,FALSE)) | G32: =IF(F32="","",TODAY()-F32) | I32: =IF(OR(B32="",D32=""),"",D32*VLOOKUP(B32,Lookup!$A$2:$B$5,2,FALSE)) | J32: =IF(OR(I32="",E32=""),"",I32*E32)

Sheet D. Patel
A1: D. Patel · Houston · Pipeline
A2: Customer | B2: Product | C2: Stage | D2: Amount ($) | E2: Probability | F2: Date Entered Stage | G2: Days in Stage | H2: Expected Close | I2: Annual Rev ($) | J2: Weighted Rev ($) | K2: Notes
A3: Zenith Software | B3: Deposits | C3: Lead | D3: 3805889.5 | E3: 0.1462 | F3: 46115 | G3: =IF(F3="","",TODAY()-F3) | H3: 46383 | I3: =IF(OR(B3="",D3=""),"",D3*VLOOKUP(B3,Lookup!$A$2:$B$5,2,FALSE)) | J3: =IF(OR(I3="",E3=""),"",I3*E3)
A4: Alamo Equipment | B4: Other Fees | C4: Lead | D4: 44796.73 | E4: 0.0978 | F4: 46113 | G4: =IF(F4="","",TODAY()-F4) | H4: 46336 | I4: =IF(OR(B4="",D4=""),"",D4*VLOOKUP(B4,Lookup!$A$2:$B$5,2,FALSE)) | J4: =IF(OR(I4="",E4=""),"",I4*E4)
A5: Brazos Petroleum | B5: Other Fees | C5: Commit | D5: 21234.43 | E5: 0.7959 | F5: 46188 | G5: =IF(F5="","",TODAY()-F5) | H5: 46244 | I5: =IF(OR(B5="",D5=""),"",D5*VLOOKUP(B5,Lookup!$A$2:$B$5,2,FALSE)) | J5: =IF(OR(I5="",E5=""),"",I5*E5)
A6: Cedar Cabinetry | B6: Deposits | C6: Qualified | D6: 664568.04 | E6: 0.2805 | F6: 46184 | G6: =IF(F6="","",TODAY()-F6) | H6: 46339 | I6: =IF(OR(B6="",D6=""),"",D6*VLOOKUP(B6,Lookup!$A$2:$B$5,2,FALSE)) | J6: =IF(OR(I6="",E6=""),"",I6*E6)
A7: Driftwood Hotels | B7: Other Fees | C7: Proposal | D7: 51592.1 | E7: 0.5394 | F7: 46175 | G7: =IF(F7="","",TODAY()-F7) | H7: 46310 | I7: =IF(OR(B7="",D7=""),"",D7*VLOOKUP(B7,Lookup!$A$2:$B$5,2,FALSE)) | J7: =IF(OR(I7="",E7=""),"",I7*E7)
A8: Acme Holdings | B8: Deposits | C8: Commit | D8: 5523470.1 | E8: 0.7583 | F8: 46130 | G8: =IF(F8="","",TODAY()-F8) | H8: 46253 | I8: =IF(OR(B8="",D8=""),"",D8*VLOOKUP(B8,Lookup!$A$2:$B$5,2,FALSE)) | J8: =IF(OR(I8="",E8=""),"",I8*E8)
A9: Beacon Industries | B9: Treasury Mgmt | C9: Proposal | D9: 154984.05 | E9: 0.5372 | F9: 46123 | G9: =IF(F9="","",TODAY()-F9) | H9: 46286 | I9: =IF(OR(B9="",D9=""),"",D9*VLOOKUP(B9,Lookup!$A$2:$B$5,2,FALSE)) | J9: =IF(OR(I9="",E9=""),"",I9*E9)
A10: Cypress Group | B10: Comm Loan | C10: Lead | D10: 1294674.4 | E10: 0.1322 | F10: 46140 | G10: =IF(F10="","",TODAY()-F10) | H10: 46364 | I10: =IF(OR(B10="",D10=""),"",D10*VLOOKUP(B10,Lookup!$A$2:$B$5,2,FALSE)) | J10: =IF(OR(I10="",E10=""),"",I10*E10)
A11: Delta Manufacturing | B11: Comm Loan | C11: Closed | D11: 670519.57 | E11: 1 | F11: 46192 | G11: =IF(F11="","",TODAY()-F11) | H11: 46216 | I11: =IF(OR(B11="",D11=""),"",D11*VLOOKUP(B11,Lookup!$A$2:$B$5,2,FALSE)) | J11: =IF(OR(I11="",E11=""),"",I11*E11)
A12: Evergreen Realty | B12: Comm Loan | C12: Commit | D12: 7093495.9 | E12: 0.8165 | F12: 46150 | G12: =IF(F12="","",TODAY()-F12) | H12: 46262 | I12: =IF(OR(B12="",D12=""),"",D12*VLOOKUP(B12,Lookup!$A$2:$B$5,2,FALSE)) | J12: =IF(OR(I12="",E12=""),"",I12*E12)
A13: Galleon Logistics | B13: Comm Loan | C13: Qualified | D13: 3025189.4 | E13: 0.259 | F13: 46174 | G13: =IF(F13="","",TODAY()-F13) | H13: 46328 | I13: =IF(OR(B13="",D13=""),"",D13*VLOOKUP(B13,Lookup!$A$2:$B$5,2,FALSE)) | J13: =IF(OR(I13="",E13=""),"",I13*E13)
A14: Harbor Partners | B14: Treasury Mgmt | C14: Qualified | D14: 118290.88 | E14: 0.2855 | F14: 46170 | G14: =IF(F14="","",TODAY()-F14) | H14: 46295 | I14: =IF(OR(B14="",D14=""),"",D14*VLOOKUP(B14,Lookup!$A$2:$B$5,2,FALSE)) | J14: =IF(OR(I14="",E14=""),"",I14*E14)
... A16: Juniper Foods | B16: Comm Loan | C16: Closed | D16: 1212020.7 | E16: 1 | F16: 46169 | G16: =IF(F16="","",TODAY()-F16) | H16: 46229 | I16: =IF(OR(B16="",D16=""),"",D16*VLOOKUP(B16,Lookup!$A$2:$B$5,2,FALSE)) | J16: =IF(OR(I16="",E16=""),"",I16*E16)
E17: =IF(C17="","",VLOOKUP(C17,Lookup!$D$2:$E$6,2,FALSE)) | G17: =IF(F17="","",TODAY()-F17) | I17: =IF(OR(B17="",D17=""),"",D17*VLOOKUP(B17,Lookup!$A$2:$B$5,2,FALSE)) | J17: =IF(OR(I17="",E17=""),"",I17*E17)
E18: =IF(C18="","",VLOOKUP(C18,Lookup!$D$2:$E$6,2,FALSE)) | G18: =IF(F18="","",TODAY()-F18) | I18: =IF(OR(B18="",D18=""),"",D18*VLOOKUP(B18,Lookup!$A$2:$B$5,2,FALSE)) | J18: =IF(OR(I18="",E18=""),"",I18*E18)
E19: =IF(C19="","",VLOOKUP(C19,Lookup!$D$2:$E$6,2,FALSE)) | G19: =IF(F19="","",TODAY()-F19) | I19: =IF(OR(B19="",D19=""),"",D19*VLOOKUP(B19,Lookup!$A$2:$B$5,2,FALSE)) | J19: =IF(OR(I19="",E19=""),"",I19*E19)
E20: =IF(C20="","",VLOOKUP(C20,Lookup!$D$2:$E$6,2,FALSE)) | G20: =IF(F20="","",TODAY()-F20) | I20: =IF(OR(B20="",D20=""),"",D20*VLOOKUP(B20,Lookup!$A$2:$B$5,2,FALSE)) | J20: =IF(OR(I20="",E20=""),"",I20*E20)
E21: =IF(C21="","",VLOOKUP(C21,Lookup!$D$2:$E$6,2,FALSE)) | G21: =IF(F21="","",TODAY()-F21) | I21: =IF(OR(B21="",D21=""),"",D21*VLOOKUP(B21,Lookup!$A$2:$B$5,2,FALSE)) | J21: =IF(OR(I21="",E21=""),"",I21*E21)
E22: =IF(C22="","",VLOOKUP(C22,Lookup!$D$2:$E$6,2,FALSE)) | G22: =IF(F22="","",TODAY()-F22) | I22: =IF(OR(B22="",D22=""),"",D22*VLOOKUP(B22,Lookup!$A$2:$B$5,2,FALSE)) | J22: =IF(OR(I22="",E22=""),"",I22*E22)
E23: =IF(C23="","",VLOOKUP(C23,Lookup!$D$2:$E$6,2,FALSE)) | G23: =IF(F23="","",TODAY()-F23) | I23: =IF(OR(B23="",D23=""),"",D23*VLOOKUP(B23,Lookup!$A$2:$B$5,2,FALSE)) | J23: =IF(OR(I23="",E23=""),"",I23*E23)
E24: =IF(C24="","",VLOOKUP(C24,Lookup!$D$2:$E$6,2,FALSE)) | G24: =IF(F24="","",TODAY()-F24) | I24: =IF(OR(B24="",D24=""),"",D24*VLOOKUP(B24,Lookup!$A$2:$B$5,2,FALSE)) | J24: =IF(OR(I24="",E24=""),"",I24*E24)
E25: =IF(C25="","",VLOOKUP(C25,Lookup!$D$2:$E$6,2,FALSE)) | G25: =IF(F25="","",TODAY()-F25) | I25: =IF(OR(B25="",D25=""),"",D25*VLOOKUP(B25,Lookup!$A$2:$B$5,2,FALSE)) | J25: =IF(OR(I25="",E25=""),"",I25*E25)
E26: =IF(C26="","",VLOOKUP(C26,Lookup!$D$2:$E$6,2,FALSE)) | G26: =IF(F26="","",TODAY()-F26) | I26: =IF(OR(B26="",D26=""),"",D26*VLOOKUP(B26,Lookup!$A$2:$B$5,2,FALSE)) | J26: =IF(OR(I26="",E26=""),"",I26*E26)
E27: =IF(C27="","",VLOOKUP(C27,Lookup!$D$2:$E$6,2,FALSE)) | G27: =IF(F27="","",TODAY()-F27) | I27: =IF(OR(B27="",D27=""),"",D27*VLOOKUP(B27,Lookup!$A$2:$B$5,2,FALSE)) | J27: =IF(OR(I27="",E27=""),"",I27*E27)
E28: =IF(C28="","",VLOOKUP(C28,Lookup!$D$2:$E$6,2,FALSE)) | G28: =IF(F28="","",TODAY()-F28) | I28: =IF(OR(B28="",D28=""),"",D28*VLOOKUP(B28,Lookup!$A$2:$B$5,2,FALSE)) | J28: =IF(OR(I28="",E28=""),"",I28*E28)
... E32: =IF(C32="","",VLOOKUP(C32,Lookup!$D$2:$E$6,2,FALSE)) | G32: =IF(F32="","",TODAY()-F32) | I32: =IF(OR(B32="",D32=""),"",D32*VLOOKUP(B32,Lookup!$A$2:$B$5,2,FALSE)) | J32: =IF(OR(I32="",E32=""),"",I32*E32)

Sheet A. Tran
A1: A. Tran · Houston · Pipeline
A2: Customer | B2: Product | C2: Stage | D2: Amount ($) | E2: Probability | F2: Date Entered Stage | G2: Days in Stage | H2: Expected Close | I2: Annual Rev ($) | J2: Weighted Rev ($) | K2: Notes
A3: Cedar Cabinetry | B3: Comm Loan | C3: Lead | D3: 1005286.4 | E3: 0.0581 | F3: 46129 | G3: =IF(F3="","",TODAY()-F3) | H3: 46337 | I3: =IF(OR(B3="",D3=""),"",D3*VLOOKUP(B3,Lookup!$A$2:$B$5,2,FALSE)) | J3: =IF(OR(I3="",E3=""),"",I3*E3)
A4: Driftwood Hotels | B4: Treasury Mgmt | C4: Commit | D4: 76930.69 | E4: 0.764 | F4: 46120 | G4: =IF(F4="","",TODAY()-F4) | H4: 46269 | I4: =IF(OR(B4="",D4=""),"",D4*VLOOKUP(B4,Lookup!$A$2:$B$5,2,FALSE)) | J4: =IF(OR(I4="",E4=""),"",I4*E4)
A5: Acme Holdings | B5: Comm Loan | C5: Qualified | D5: 8942929.7 | E5: 0.2501 | F5: 46163 | G5: =IF(F5="","",TODAY()-F5) | H5: 46326 | I5: =IF(OR(B5="",D5=""),"",D5*VLOOKUP(B5,Lookup!$A$2:$B$5,2,FALSE)) | J5: =IF(OR(I5="",E5=""),"",I5*E5)
A6: Beacon Industries | B6: Deposits | C6: Lead | D6: 2437446.8 | E6: 0.1449 | F6: 46192 | G6: =IF(F6="","",TODAY()-F6) | H6: 46330 | I6: =IF(OR(B6="",D6=""),"",D6*VLOOKUP(B6,Lookup!$A$2:$B$5,2,FALSE)) | J6: =IF(OR(I6="",E6=""),"",I6*E6)
A7: Cypress Group | B7: Comm Loan | C7: Proposal | D7: 6584533.2 | E7: 0.4954 | F7: 46134 | G7: =IF(F7="","",TODAY()-F7) | H7: 46298 | I7: =IF(OR(B7="",D7=""),"",D7*VLOOKUP(B7,Lookup!$A$2:$B$5,2,FALSE)) | J7: =IF(OR(I7="",E7=""),"",I7*E7)
A8: Delta Manufacturing | B8: Other Fees | C8: Qualified | D8: 26664.61 | E8: 0.2668 | F8: 46183 | G8: =IF(F8="","",TODAY()-F8) | H8: 46350 | I8: =IF(OR(B8="",D8=""),"",D8*VLOOKUP(B8,Lookup!$A$2:$B$5,2,FALSE)) | J8: =IF(OR(I8="",E8=""),"",I8*E8)
A9: Evergreen Realty | B9: Other Fees | C9: Proposal | D9: 67794 | E9: 0.5078 | F9: 46193 | G9: =IF(F9="","",TODAY()-F9) | H9: 46274 | I9: =IF(OR(B9="",D9=""),"",D9*VLOOKUP(B9,Lookup!$A$2:$B$5,2,FALSE)) | J9: =IF(OR(I9="",E9=""),"",I9*E9)
A10: Fairfield Energy | B10: Deposits | C10: Closed | D10: 713863.45 | E10: 1 | F10: 46164 | G10: =IF(F10="","",TODAY()-F10) | H10: 46228 | I10: =IF(OR(B10="",D10=""),"",D10*VLOOKUP(B10,Lookup!$A$2:$B$5,2,FALSE)) | J10: =IF(OR(I10="",E10=""),"",I10*E10)
A11: Galleon Logistics | B11: Comm Loan | C11: Proposal | D11: 4952275.3 | E11: 0.5301 | F11: 46191 | G11: =IF(F11="","",TODAY()-F11) | H11: 46313 | I11: =IF(OR(B11="",D11=""),"",D11*VLOOKUP(B11,Lookup!$A$2:$B$5,2,FALSE)) | J11: =IF(OR(I11="",E11=""),"",I11*E11)
A12: Harbor Partners | B12: Comm Loan | C12: Lead | D12: 16637852 | E12: 0.1183 | F12: 46145 | G12: =IF(F12="","",TODAY()-F12) | H12: 46370 | I12: =IF(OR(B12="",D12=""),"",D12*VLOOKUP(B12,Lookup!$A$2:$B$5,2,FALSE)) | J12: =IF(OR(I12="",E12=""),"",I12*E12)
A13: Harbor Partners | B13: Deposits | C13: Lead | D13: 2865543 | E13: 0.1356 | F13: 46138 | G13: =IF(F13="","",TODAY()-F13) | H13: 46326 | I13: =IF(OR(B13="",D13=""),"",D13*VLOOKUP(B13,Lookup!$A$2:$B$5,2,FALSE)) | J13: =IF(OR(I13="",E13=""),"",I13*E13)
E14: =IF(C14="","",VLOOKUP(C14,Lookup!$D$2:$E$6,2,FALSE)) | G14: =IF(F14="","",TODAY()-F14) | I14: =IF(OR(B14="",D14=""),"",D14*VLOOKUP(B14,Lookup!$A$2:$B$5,2,FALSE)) | J14: =IF(OR(I14="",E14=""),"",I14*E14)
E15: =IF(C15="","",VLOOKUP(C15,Lookup!$D$2:$E$6,2,FALSE)) | G15: =IF(F15="","",TODAY()-F15) | I15: =IF(OR(B15="",D15=""),"",D15*VLOOKUP(B15,Lookup!$A$2:$B$5,2,FALSE)) | J15: =IF(OR(I15="",E15=""),"",I15*E15)
E16: =IF(C16="","",VLOOKUP(C16,Lookup!$D$2:$E$6,2,FALSE)) | G16: =IF(F16="","",TODAY()-F16) | I16: =IF(OR(B16="",D16=""),"",D16*VLOOKUP(B16,Lookup!$A$2:$B$5,2,FALSE)) | J16: =IF(OR(I16="",E16=""),"",I16*E16)
E17: =IF(C17="","",VLOOKUP(C17,Lookup!$D$2:$E$6,2,FALSE)) | G17: =IF(F17="","",TODAY()-F17) | I17: =IF(OR(B17="",D17=""),"",D17*VLOOKUP(B17,Lookup!$A$2:$B$5,2,FALSE)) | J17: =IF(OR(I17="",E17=""),"",I17*E17)
E18: =IF(C18="","",VLOOKUP(C18,Lookup!$D$2:$E$6,2,FALSE)) | G18: =IF(F18="","",TODAY()-F18) | I18: =IF(OR(B18="",D18=""),"",D18*VLOOKUP(B18,Lookup!$A$2:$B$5,2,FALSE)) | J18: =IF(OR(I18="",E18=""),"",I18*E18)
E19: =IF(C19="","",VLOOKUP(C19,Lookup!$D$2:$E$6,2,FALSE)) | G19: =IF(F19="","",TODAY()-F19) | I19: =IF(OR(B19="",D19=""),"",D19*VLOOKUP(B19,Lookup!$A$2:$B$5,2,FALSE)) | J19: =IF(OR(I19="",E19=""),"",I19*E19)
E20: =IF(C20="","",VLOOKUP(C20,Lookup!$D$2:$E$6,2,FALSE)) | G20: =IF(F20="","",TODAY()-F20) | I20: =IF(OR(B20="",D20=""),"",D20*VLOOKUP(B20,Lookup!$A$2:$B$5,2,FALSE)) | J20: =IF(OR(I20="",E20=""),"",I20*E20)
E21: =IF(C21="","",VLOOKUP(C21,Lookup!$D$2:$E$6,2,FALSE)) | G21: =IF(F21="","",TODAY()-F21) | I21: =IF(OR(B21="",D21=""),"",D21*VLOOKUP(B21,Lookup!$A$2:$B$5,2,FALSE)) | J21: =IF(OR(I21="",E21=""),"",I21*E21)
E22: =IF(C22="","",VLOOKUP(C22,Lookup!$D$2:$E$6,2,FALSE)) | G22: =IF(F22="","",TODAY()-F22) | I22: =IF(OR(B22="",D22=""),"",D22*VLOOKUP(B22,Lookup!$A$2:$B$5,2,FALSE)) | J22: =IF(OR(I22="",E22=""),"",I22*E22)
E23: =IF(C23="","",VLOOKUP(C23,Lookup!$D$2:$E$6,2,FALSE)) | G23: =IF(F23="","",TODAY()-F23) | I23: =IF(OR(B23="",D23=""),"",D23*VLOOKUP(B23,Lookup!$A$2:$B$5,2,FALSE)) | J23: =IF(OR(I23="",E23=""),"",I23*E23)
E24: =IF(C24="","",VLOOKUP(C24,Lookup!$D$2:$E$6,2,FALSE)) | G24: =IF(F24="","",TODAY()-F24) | I24: =IF(OR(B24="",D24=""),"",D24*VLOOKUP(B24,Lookup!$A$2:$B$5,2,FALSE)) | J24: =IF(OR(I24="",E24=""),"",I24*E24)
E25: =IF(C25="","",VLOOKUP(C25,Lookup!$D$2:$E$6,2,FALSE)) | G25: =IF(F25="","",TODAY()-F25) | I25: =IF(OR(B25="",D25=""),"",D25*VLOOKUP(B25,Lookup!$A$2:$B$5,2,FALSE)) | J25: =IF(OR(I25="",E25=""),"",I25*E25)
... E32: =IF(C32="","",VLOOKUP(C32,Lookup!$D$2:$E$6,2,FALSE)) | G32: =IF(F32="","",TODAY()-F32) | I32: =IF(OR(B32="",D32=""),"",D32*VLOOKUP(B32,Lookup!$A$2:$B$5,2,FALSE)) | J32: =IF(OR(I32="",E32=""),"",I32*E32)

Sheet K. Williams
A1: K. Williams · Houston · Pipeline
A2: Customer | B2: Product | C2: Stage | D2: Amount ($) | E2: Probability | F2: Date Entered Stage | G2: Days in Stage | H2: Expected Close | I2: Annual Rev ($) | J2: Weighted Rev ($) | K2: Notes
A3: Harbor Partners | B3: Comm Loan | C3: Lead | D3: 15724903 | E3: 0.0583 | F3: 46126 | G3: =IF(F3="","",TODAY()-F3) | H3: 46378 | I3: =IF(OR(B3="",D3=""),"",D3*VLOOKUP(B3,Lookup!$A$2:$B$5,2,FALSE)) | J3: =IF(OR(I3="",E3=""),"",I3*E3)
A4: Ironwood Capital | B4: Deposits | C4: Lead | D4: 933487.87 | E4: 0.1089 | F4: 46139 | G4: =IF(F4="","",TODAY()-F4) | H4: 46375 | I4: =IF(OR(B4="",D4=""),"",D4*VLOOKUP(B4,Lookup!$A$2:$B$5,2,FALSE)) | J4: =IF(OR(I4="",E4=""),"",I4*E4)
A5: Juniper Foods | B5: Comm Loan | C5: Proposal | D5: 779233.08 | E5: 0.4508 | F5: 46100 | G5: =IF(F5="","",TODAY()-F5) | H5: 46276 | I5: =IF(OR(B5="",D5=""),"",D5*VLOOKUP(B5,Lookup!$A$2:$B$5,2,FALSE)) | J5: =IF(OR(I5="",E5=""),"",I5*E5)
A6: Keystone Steel | B6: Comm Loan | C6: Qualified | D6: 2585647.3 | E6: 0.2363 | F6: 46114 | G6: =IF(F6="","",TODAY()-F6) | H6: 46314 | I6: =IF(OR(B6="",D6=""),"",D6*VLOOKUP(B6,Lookup!$A$2:$B$5,2,FALSE)) | J6: =IF(OR(I6="",E6=""),"",I6*E6)
A7: Lakeside Medical | B7: Comm Loan | C7: Qualified | D7: 5200728.9 | E7: 0.2737 | F7: 46171 | G7: =IF(F7="","",TODAY()-F7) | H7: 46310 | I7: =IF(OR(B7="",D7=""),"",D7*VLOOKUP(B7,Lookup!$A$2:$B$5,2,FALSE)) | J7: =IF(OR(I7="",E7=""),"",I7*E7)
A8: Mason & Co. | B8: Other Fees | C8: Lead | D8: 22812.17 | E8: 0.0764 | F8: 46033 | G8: =IF(F8="","",TODAY()-F8) | H8: 46383 | I8: =IF(OR(B8="",D8=""),"",D8*VLOOKUP(B8,Lookup!$A$2:$B$5,2,FALSE)) | J8: =IF(OR(I8="",E8=""),"",I8*E8)
A9: Northstar Tech | B9: Comm Loan | C9: Lead | D9: 7356362.1 | E9: 0.0874 | F9: 46188 | G9: =IF(F9="","",TODAY()-F9) | H9: 46377 | I9: =IF(OR(B9="",D9=""),"",D9*VLOOKUP(B9,Lookup!$A$2:$B$5,2,FALSE)) | J9: =IF(OR(I9="",E9=""),"",I9*E9)
E10: =IF(C10="","",VLOOKUP(C10,Lookup!$D$2:$E$6,2,FALSE)) | G10: =IF(F10="","",TODAY()-F10) | I10: =IF(OR(B10="",D10=""),"",D10*VLOOKUP(B10,Lookup!$A$2:$B$5,2,FALSE)) | J10: =IF(OR(I10="",E10=""),"",I10*E10)
E11: =IF(C11="","",VLOOKUP(C11,Lookup!$D$2:$E$6,2,FALSE)) | G11: =IF(F11="","",TODAY()-F11) | I11: =IF(OR(B11="",D11=""),"",D11*VLOOKUP(B11,Lookup!$A$2:$B$5,2,FALSE)) | J11: =IF(OR(I11="",E11=""),"",I11*E11)
E12: =IF(C12="","",VLOOKUP(C12,Lookup!$D$2:$E$6,2,FALSE)) | G12: =IF(F12="","",TODAY()-F12) | I12: =IF(OR(B12="",D12=""),"",D12*VLOOKUP(B12,Lookup!$A$2:$B$5,2,FALSE)) | J12: =IF(OR(I12="",E12=""),"",I12*E12)
E13: =IF(C13="","",VLOOKUP(C13,Lookup!$D$2:$E$6,2,FALSE)) | G13: =IF(F13="","",TODAY()-F13) | I13: =IF(OR(B13="",D13=""),"",D13*VLOOKUP(B13,Lookup!$A$2:$B$5,2,FALSE)) | J13: =IF(OR(I13="",E13=""),"",I13*E13)
E14: =IF(C14="","",VLOOKUP(C14,Lookup!$D$2:$E$6,2,FALSE)) | G14: =IF(F14="","",TODAY()-F14) | I14: =IF(OR(B14="",D14=""),"",D14*VLOOKUP(B14,Lookup!$A$2:$B$5,2,FALSE)) | J14: =IF(OR(I14="",E14=""),"",I14*E14)
E15: =IF(C15="","",VLOOKUP(C15,Lookup!$D$2:$E$6,2,FALSE)) | G15: =IF(F15="","",TODAY()-F15) | I15: =IF(OR(B15="",D15=""),"",D15*VLOOKUP(B15,Lookup!$A$2:$B$5,2,FALSE)) | J15: =IF(OR(I15="",E15=""),"",I15*E15)
E16: =IF(C16="","",VLOOKUP(C16,Lookup!$D$2:$E$6,2,FALSE)) | G16: =IF(F16="","",TODAY()-F16) | I16: =IF(OR(B16="",D16=""),"",D16*VLOOKUP(B16,Lookup!$A$2:$B$5,2,FALSE)) | J16: =IF(OR(I16="",E16=""),"",I16*E16)
E17: =IF(C17="","",VLOOKUP(C17,Lookup!$D$2:$E$6,2,FALSE)) | G17: =IF(F17="","",TODAY()-F17) | I17: =IF(OR(B17="",D17=""),"",D17*VLOOKUP(B17,Lookup!$A$2:$B$5,2,FALSE)) | J17: =IF(OR(I17="",E17=""),"",I17*E17)
E18: =IF(C18="","",VLOOKUP(C18,Lookup!$D$2:$E$6,2,FALSE)) | G18: =IF(F18="","",TODAY()-F18) | I18: =IF(OR(B18="",D18=""),"",D18*VLOOKUP(B18,Lookup!$A$2:$B$5,2,FALSE)) | J18: =IF(OR(I18="",E18=""),"",I18*E18)
E19: =IF(C19="","",VLOOKUP(C19,Lookup!$D$2:$E$6,2,FALSE)) | G19: =IF(F19="","",TODAY()-F19) | I19: =IF(OR(B19="",D19=""),"",D19*VLOOKUP(B19,Lookup!$A$2:$B$5,2,FALSE)) | J19: =IF(OR(I19="",E19=""),"",I19*E19)
E20: =IF(C20="","",VLOOKUP(C20,Lookup!$D$2:$E$6,2,FALSE)) | G20: =IF(F20="","",TODAY()-F20) | I20: =IF(OR(B20="",D20=""),"",D20*VLOOKUP(B20,Lookup!$A$2:$B$5,2,FALSE)) | J20: =IF(OR(I20="",E20=""),"",I20*E20)
E21: =IF(C21="","",VLOOKUP(C21,Lookup!$D$2:$E$6,2,FALSE)) | G21: =IF(F21="","",TODAY()-F21) | I21: =IF(OR(B21="",D21=""),"",D21*VLOOKUP(B21,Lookup!$A$2:$B$5,2,FALSE)) | J21: =IF(OR(I21="",E21=""),"",I21*E21)
... E32: =IF(C32="","",VLOOKUP(C32,Lookup!$D$2:$E$6,2,FALSE)) | G32: =IF(F32="","",TODAY()-F32) | I32: =IF(OR(B32="",D32=""),"",D32*VLOOKUP(B32,Lookup!$A$2:$B$5,2,FALSE)) | J32: =IF(OR(I32="",E32=""),"",I32*E32)

Sheet R. Chen
A1: R. Chen · Dallas · Pipeline
A2: Customer | B2: Product | C2: Stage | D2: Amount ($) | E2: Probability | F2: Date Entered Stage | G2: Days in Stage | H2: Expected Close | I2: Annual Rev ($) | J2: Weighted Rev ($) | K2: Notes
A3: Redwood Construction | B3: Comm Loan | C3: Commit | D3: 17680676 | E3: 0.7914 | F3: 46142 | G3: =IF(F3="","",TODAY()-F3) | H3: 46261 | I3: =IF(OR(B3="",D3=""),"",D3*VLOOKUP(B3,Lookup!$A$2:$B$5,2,FALSE)) | J3: =IF(OR(I3="",E3=""),"",I3*E3)
A4: Summit Hospitality | B4: Comm Loan | C4: Proposal | D4: 2595942.8 | E4: 0.4503 | F4: 46142 | G4: =IF(F4="","",TODAY()-F4) | H4: 46307 | I4: =IF(OR(B4="",D4=""),"",D4*VLOOKUP(B4,Lookup!$A$2:$B$5,2,FALSE)) | J4: =IF(OR(I4="",E4=""),"",I4*E4)
A5: Trinity Pharma | B5: Comm Loan | C5: Lead | D5: 10550099 | E5: 0.0508 | F5: 46137 | G5: =IF(F5="","",TODAY()-F5) | H5: 46352 | I5: =IF(OR(B5="",D5=""),"",D5*VLOOKUP(B5,Lookup!$A$2:$B$5,2,FALSE)) | J5: =IF(OR(I5="",E5=""),"",I5*E5)
A6: Union Distributors | B6: Deposits | C6: Qualified | D6: 1055220.3 | E6: 0.2275 | F6: 46182 | G6: =IF(F6="","",TODAY()-F6) | H6: 46337 | I6: =IF(OR(B6="",D6=""),"",D6*VLOOKUP(B6,Lookup!$A$2:$B$5,2,FALSE)) | J6: =IF(OR(I6="",E6=""),"",I6*E6)
A7: Vanguard Plastics | B7: Deposits | C7: Qualified | D7: 4639920.4 | E7: 0.2146 | F7: 46126 | G7: =IF(F7="","",TODAY()-F7) | H7: 46330 | I7: =IF(OR(B7="",D7=""),"",D7*VLOOKUP(B7,Lookup!$A$2:$B$5,2,FALSE)) | J7: =IF(OR(I7="",E7=""),"",I7*E7)
A8: Westfield Retail | B8: Comm Loan | C8: Lead | D8: 1585817.7 | E8: 0.1178 | F8: 46167 | G8: =IF(F8="","",TODAY()-F8) | H8: 46331 | I8: =IF(OR(B8="",D8=""),"",D8*VLOOKUP(B8,Lookup!$A$2:$B$5,2,FALSE)) | J8: =IF(OR(I8="",E8=""),"",I8*E8)
A9: Xander Aviation | B9: Comm Loan | C9: Lead | D9: 2728841.3 | E9: 0.1017 | F9: 46182 | G9: =IF(F9="","",TODAY()-F9) | H9: 46363 | I9: =IF(OR(B9="",D9=""),"",D9*VLOOKUP(B9,Lookup!$A$2:$B$5,2,FALSE)) | J9: =IF(OR(I9="",E9=""),"",I9*E9)
A10: Yellowstone Ranch | B10: Other Fees | C10: Proposal | D10: 24484.22 | E10: 0.4725 | F10: 46115 | G10: =IF(F10="","",TODAY()-F10) | H10: 46270 | I10: =IF(OR(B10="",D10=""),"",D10*VLOOKUP(B10,Lookup!$A$2:$B$5,2,FALSE)) | J10: =IF(OR(I10="",E10=""),"",I10*E10)
A11: Zenith Software | B11: Deposits | C11: Lead | D11: 3267346.2 | E11: 0.117 | F11: 46162 | G11: =IF(F11="","",TODAY()-F11) | H11: 46333 | I11: =IF(OR(B11="",D11=""),"",D11*VLOOKUP(B11,Lookup!$A$2:$B$5,2,FALSE)) | J11: =IF(OR(I11="",E11=""),"",I11*E11)
E12: =IF(C12="","",VLOOKUP(C12,Lookup!$D$2:$E$6,2,FALSE)) | G12: =IF(F12="","",TODAY()-F12) | I12: =IF(OR(B12="",D12=""),"",D12*VLOOKUP(B12,Lookup!$A$2:$B$5,2,FALSE)) | J12: =IF(OR(I12="",E12=""),"",I12*E12)
E13: =IF(C13="","",VLOOKUP(C13,Lookup!$D$2:$E$6,2,FALSE)) | G13: =IF(F13="","",TODAY()-F13) | I13: =IF(OR(B13="",D13=""),"",D13*VLOOKUP(B13,Lookup!$A$2:$B$5,2,FALSE)) | J13: =IF(OR(I13="",E13=""),"",I13*E13)
E14: =IF(C14="","",VLOOKUP(C14,Lookup!$D$2:$E$6,2,FALSE)) | G14: =IF(F14="","",TODAY()-F14) | I14: =IF(OR(B14="",D14=""),"",D14*VLOOKUP(B14,Lookup!$A$2:$B$5,2,FALSE)) | J14: =IF(OR(I14="",E14=""),"",I14*E14)
E15: =IF(C15="","",VLOOKUP(C15,Lookup!$D$2:$E$6,2,FALSE)) | G15: =IF(F15="","",TODAY()-F15) | I15: =IF(OR(B15="",D15=""),"",D15*VLOOKUP(B15,Lookup!$A$2:$B$5,2,FALSE)) | J15: =IF(OR(I15="",E15=""),"",I15*E15)
E16: =IF(C16="","",VLOOKUP(C16,Lookup!$D$2:$E$6,2,FALSE)) | G16: =IF(F16="","",TODAY()-F16) | I16: =IF(OR(B16="",D16=""),"",D16*VLOOKUP(B16,Lookup!$A$2:$B$5,2,FALSE)) | J16: =IF(OR(I16="",E16=""),"",I16*E16)
E17: =IF(C17="","",VLOOKUP(C17,Lookup!$D$2:$E$6,2,FALSE)) | G17: =IF(F17="","",TODAY()-F17) | I17: =IF(OR(B17="",D17=""),"",D17*VLOOKUP(B17,Lookup!$A$2:$B$5,2,FALSE)) | J17: =IF(OR(I17="",E17=""),"",I17*E17)
E18: =IF(C18="","",VLOOKUP(C18,Lookup!$D$2:$E$6,2,FALSE)) | G18: =IF(F18="","",TODAY()-F18) | I18: =IF(OR(B18="",D18=""),"",D18*VLOOKUP(B18,Lookup!$A$2:$B$5,2,FALSE)) | J18: =IF(OR(I18="",E18=""),"",I18*E18)
E19: =IF(C19="","",VLOOKUP(C19,Lookup!$D$2:$E$6,2,FALSE)) | G19: =IF(F19="","",TODAY()-F19) | I19: =IF(OR(B19="",D19=""),"",D19*VLOOKUP(B19,Lookup!$A$2:$B$5,2,FALSE)) | J19: =IF(OR(I19="",E19=""),"",I19*E19)
E20: =IF(C20="","",VLOOKUP(C20,Lookup!$D$2:$E$6,2,FALSE)) | G20: =IF(F20="","",TODAY()-F20) | I20: =IF(OR(B20="",D20=""),"",D20*VLOOKUP(B20,Lookup!$A$2:$B$5,2,FALSE)) | J20: =IF(OR(I20="",E20=""),"",I20*E20)
E21: =IF(C21="","",VLOOKUP(C21,Lookup!$D$2:$E$6,2,FALSE)) | G21: =IF(F21="","",TODAY()-F21) | I21: =IF(OR(B21="",D21=""),"",D21*VLOOKUP(B21,Lookup!$A$2:$B$5,2,FALSE)) | J21: =IF(OR(I21="",E21=""),"",I21*E21)
E22: =IF(C22="","",VLOOKUP(C22,Lookup!$D$2:$E$6,2,FALSE)) | G22: =IF(F22="","",TODAY()-F22) | I22: =IF(OR(B22="",D22=""),"",D22*VLOOKUP(B22,Lookup!$A$2:$B$5,2,FALSE)) | J22: =IF(OR(I22="",E22=""),"",I22*E22)
E23: =IF(C23="","",VLOOKUP(C23,Lookup!$D$2:$E$6,2,FALSE)) | G23: =IF(F23="","",TODAY()-F23) | I23: =IF(OR(B23="",D23=""),"",D23*VLOOKUP(B23,Lookup!$A$2:$B$5,2,FALSE)) | J23: =IF(OR(I23="",E23=""),"",I23*E23)
... E32: =IF(C32="","",VLOOKUP(C32,Lookup!$D$2:$E$6,2,FALSE)) | G32: =IF(F32="","",TODAY()-F32) | I32: =IF(OR(B32="",D32=""),"",D32*VLOOKUP(B32,Lookup!$A$2:$B$5,2,FALSE)) | J32: =IF(OR(I32="",E32=""),"",I32*E32)

Sheet S. Garcia
A1: S. Garcia · Dallas · Pipeline
A2: Customer | B2: Product | C2: Stage | D2: Amount ($) | E2: Probability | F2: Date Entered Stage | G2: Days in Stage | H2: Expected Close | I2: Annual Rev ($) | J2: Weighted Rev ($) | K2: Notes
A3: Union Distributors | B3: Other Fees | C3: Qualified | D3: 49498.92 | E3: 0.2127 | F3: 46081 | G3: =IF(F3="","",TODAY()-F3) | H3: 46337 | I3: =IF(OR(B3="",D3=""),"",D3*VLOOKUP(B3,Lookup!$A$2:$B$5,2,FALSE)) | J3: =IF(OR(I3="",E3=""),"",I3*E3)
A4: Vanguard Plastics | B4: Treasury Mgmt | C4: Lead | D4: 117786.33 | E4: 0.1338 | F4: 46143 | G4: =IF(F4="","",TODAY()-F4) | H4: 46376 | I4: =IF(OR(B4="",D4=""),"",D4*VLOOKUP(B4,Lookup!$A$2:$B$5,2,FALSE)) | J4: =IF(OR(I4="",E4=""),"",I4*E4)
A5: Westfield Retail | B5: Comm Loan | C5: Closed | D5: 3693911.7 | E5: 1 | F5: 46098 | G5: =IF(F5="","",TODAY()-F5) | H5: 46213 | I5: =IF(OR(B5="",D5=""),"",D5*VLOOKUP(B5,Lookup!$A$2:$B$5,2,FALSE)) | J5: =IF(OR(I5="",E5=""),"",I5*E5)
A6: Xander Aviation | B6: Other Fees | C6: Lead | D6: 40457.68 | E6: 0.1036 | F6: 46135 | G6: =IF(F6="","",TODAY()-F6) | H6: 46383 | I6: =IF(OR(B6="",D6=""),"",D6*VLOOKUP(B6,Lookup!$A$2:$B$5,2,FALSE)) | J6: =IF(OR(I6="",E6=""),"",I6*E6)
A7: Yellowstone Ranch | B7: Comm Loan | C7: Qualified | D7: 2322589.7 | E7: 0.2114 | F7: 46078 | G7: =IF(F7="","",TODAY()-F7) | H7: 46343 | I7: =IF(OR(B7="",D7=""),"",D7*VLOOKUP(B7,Lookup!$A$2:$B$5,2,FALSE)) | J7: =IF(OR(I7="",E7=""),"",I7*E7)
A8: Zenith Software | B8: Deposits | C8: Proposal | D8: 5664478.3 | E8: 0.5112 | F8: 46151 | G8: =IF(F8="","",TODAY()-F8) | H8: 46299 | I8: =IF(OR(B8="",D8=""),"",D8*VLOOKUP(B8,Lookup!$A$2:$B$5,2,FALSE)) | J8: =IF(OR(I8="",E8=""),"",I8*E8)
A9: Alamo Equipment | B9: Treasury Mgmt | C9: Commit | D9: 250208.93 | E9: 0.8488 | F9: 46131 | G9: =IF(F9="","",TODAY()-F9) | H9: 46269 | I9: =IF(OR(B9="",D9=""),"",D9*VLOOKUP(B9,Lookup!$A$2:$B$5,2,FALSE)) | J9: =IF(OR(I9="",E9=""),"",I9*E9)
E10: =IF(C10="","",VLOOKUP(C10,Lookup!$D$2:$E$6,2,FALSE)) | G10: =IF(F10="","",TODAY()-F10) | I10: =IF(OR(B10="",D10=""),"",D10*VLOOKUP(B10,Lookup!$A$2:$B$5,2,FALSE)) | J10: =IF(OR(I10="",E10=""),"",I10*E10)
E11: =IF(C11="","",VLOOKUP(C11,Lookup!$D$2:$E$6,2,FALSE)) | G11: =IF(F11="","",TODAY()-F11) | I11: =IF(OR(B11="",D11=""),"",D11*VLOOKUP(B11,Lookup!$A$2:$B$5,2,FALSE)) | J11: =IF(OR(I11="",E11=""),"",I11*E11)
E12: =IF(C12="","",VLOOKUP(C12,Lookup!$D$2:$E$6,2,FALSE)) | G12: =IF(F12="","",TODAY()-F12) | I12: =IF(OR(B12="",D12=""),"",D12*VLOOKUP(B12,Lookup!$A$2:$B$5,2,FALSE)) | J12: =IF(OR(I12="",E12=""),"",I12*E12)
E13: =IF(C13="","",VLOOKUP(C13,Lookup!$D$2:$E$6,2,FALSE)) | G13: =IF(F13="","",TODAY()-F13) | I13: =IF(OR(B13="",D13=""),"",D13*VLOOKUP(B13,Lookup!$A$2:$B$5,2,FALSE)) | J13: =IF(OR(I13="",E13=""),"",I13*E13)
E14: =IF(C14="","",VLOOKUP(C14,Lookup!$D$2:$E$6,2,FALSE)) | G14: =IF(F14="","",TODAY()-F14) | I14: =IF(OR(B14="",D14=""),"",D14*VLOOKUP(B14,Lookup!$A$2:$B$5,2,FALSE)) | J14: =IF(OR(I14="",E14=""),"",I14*E14)
E15: =IF(C15="","",VLOOKUP(C15,Lookup!$D$2:$E$6,2,FALSE)) | G15: =IF(F15="","",TODAY()-F15) | I15: =IF(OR(B15="",D15=""),"",D15*VLOOKUP(B15,Lookup!$A$2:$B$5,2,FALSE)) | J15: =IF(OR(I15="",E15=""),"",I15*E15)
E16: =IF(C16="","",VLOOKUP(C16,Lookup!$D$2:$E$6,2,FALSE)) | G16: =IF(F16="","",TODAY()-F16) | I16: =IF(OR(B16="",D16=""),"",D16*VLOOKUP(B16,Lookup!$A$2:$B$5,2,FALSE)) | J16: =IF(OR(I16="",E16=""),"",I16*E16)
E17: =IF(C17="","",VLOOKUP(C17,Lookup!$D$2:$E$6,2,FALSE)) | G17: =IF(F17="","",TODAY()-F17) | I17: =IF(OR(B17="",D17=""),"",D17*VLOOKUP(B17,Lookup!$A$2:$B$5,2,FALSE)) | J17: =IF(OR(I17="",E17=""),"",I17*E17)
E18: =IF(C18="","",VLOOKUP(C18,Lookup!$D$2:$E$6,2,FALSE)) | G18: =IF(F18="","",TODAY()-F18) | I18: =IF(OR(B18="",D18=""),"",D18*VLOOKUP(B18,Lookup!$A$2:$B$5,2,FALSE)) | J18: =IF(OR(I18="",E18=""),"",I18*E18)
E19: =IF(C19="","",VLOOKUP(C19,Lookup!$D$2:$E$6,2,FALSE)) | G19: =IF(F19="","",TODAY()-F19) | I19: =IF(OR(B19="",D19=""),"",D19*VLOOKUP(B19,Lookup!$A$2:$B$5,2,FALSE)) | J19: =IF(OR(I19="",E19=""),"",I19*E19)
E20: =IF(C20="","",VLOOKUP(C20,Lookup!$D$2:$E$6,2,FALSE)) | G20: =IF(F20="","",TODAY()-F20) | I20: =IF(OR(B20="",D20=""),"",D20*VLOOKUP(B20,Lookup!$A$2:$B$5,2,FALSE)) | J20: =IF(OR(I20="",E20=""),"",I20*E20)
E21: =IF(C21="","",VLOOKUP(C21,Lookup!$D$2:$E$6,2,FALSE)) | G21: =IF(F21="","",TODAY()-F21) | I21: =IF(OR(B21="",D21=""),"",D21*VLOOKUP(B21,Lookup!$A$2:$B$5,2,FALSE)) | J21: =IF(OR(I21="",E21=""),"",I21*E21)
... E32: =IF(C32="","",VLOOKUP(C32,Lookup!$D$2:$E$6,2,FALSE)) | G32: =IF(F32="","",TODAY()-F32) | I32: =IF(OR(B32="",D32=""),"",D32*VLOOKUP(B32,Lookup!$A$2:$B$5,2,FALSE)) | J32: =IF(OR(I32="",E32=""),"",I32*E32)

Sheet B. Foster
A1: B. Foster · Dallas · Pipeline
A2: Customer | B2: Product | C2: Stage | D2: Amount ($) | E2: Probability | F2: Date Entered Stage | G2: Days in Stage | H2: Expected Close | I2: Annual Rev ($) | J2: Weighted Rev ($) | K2: Notes
A3: Evergreen Realty | B3: Deposits | C3: Qualified | D3: 4276478.3 | E3: 0.2008 | F3: 46129 | G3: =IF(F3="","",TODAY()-F3) | H3: 46339 | I3: =IF(OR(B3="",D3=""),"",D3*VLOOKUP(B3,Lookup!$A$2:$B$5,2,FALSE)) | J3: =IF(OR(I3="",E3=""),"",I3*E3)
A4: Fairfield Energy | B4: Other Fees | C4: Commit | D4: 71443.88 | E4: 0.8062 | F4: 46156 | G4: =IF(F4="","",TODAY()-F4) | H4: 46285 | I4: =IF(OR(B4="",D4=""),"",D4*VLOOKUP(B4,Lookup!$A$2:$B$5,2,FALSE)) | J4: =IF(OR(I4="",E4=""),"",I4*E4)
A5: Galleon Logistics | B5: Comm Loan | C5: Proposal | D5: 3318346 | E5: 0.5425 | F5: 46158 | G5: =IF(F5="","",TODAY()-F5) | H5: 46302 | I5: =IF(OR(B5="",D5=""),"",D5*VLOOKUP(B5,Lookup!$A$2:$B$5,2,FALSE)) | J5: =IF(OR(I5="",E5=""),"",I5*E5)
A6: Harbor Partners | B6: Deposits | C6: Lead | D6: 942755.35 | E6: 0.0574 | F6: 46118 | G6: =IF(F6="","",TODAY()-F6) | H6: 46337 | I6: =IF(OR(B6="",D6=""),"",D6*VLOOKUP(B6,Lookup!$A$2:$B$5,2,FALSE)) | J6: =IF(OR(I6="",E6=""),"",I6*E6)
A7: Ironwood Capital | B7: Deposits | C7: Qualified | D7: 907319.76 | E7: 0.2669 | F7: 46169 | G7: =IF(F7="","",TODAY()-F7) | H7: 46314 | I7: =IF(OR(B7="",D7=""),"",D7*VLOOKUP(B7,Lookup!$A$2:$B$5,2,FALSE)) | J7: =IF(OR(I7="",E7=""),"",I7*E7)
A8: Juniper Foods | B8: Comm Loan | C8: Qualified | D8: 14970369 | E8: 0.2907 | F8: 46168 | G8: =IF(F8="","",TODAY()-F8) | H8: 46312 | I8: =IF(OR(B8="",D8=""),"",D8*VLOOKUP(B8,Lookup!$A$2:$B$5,2,FALSE)) | J8: =IF(OR(I8="",E8=""),"",I8*E8)
A9: Keystone Steel | B9: Deposits | C9: Proposal | D9: 7146029 | E9: 0.4834 | F9: 46135 | G9: =IF(F9="","",TODAY()-F9) | H9: 46304 | I9: =IF(OR(B9="",D9=""),"",D9*VLOOKUP(B9,Lookup!$A$2:$B$5,2,FALSE)) | J9: =IF(OR(I9="",E9=""),"",I9*E9)
A10: Lakeside Medical | B10: Treasury Mgmt | C10: Closed | D10: 36610.28 | E10: 0.9827 | F10: 46189 | G10: =IF(F10="","",TODAY()-F10) | H10: 46240 | I10: =IF(OR(B10="",D10=""),"",D10*VLOOKUP(B10,Lookup!$A$2:$B$5,2,FALSE)) | J10: =IF(OR(I10="",E10=""),"",I10*E10)
A11: Mason & Co. | B11: Comm Loan | C11: Proposal | D11: 3839311.5 | E11: 0.4668 | F11: 46181 | G11: =IF(F11="","",TODAY()-F11) | H11: 46279 | I11: =IF(OR(B11="",D11=""),"",D11*VLOOKUP(B11,Lookup!$A$2:$B$5,2,FALSE)) | J11: =IF(OR(I11="",E11=""),"",I11*E11)
A12: Northstar Tech | B12: Comm Loan | C12: Proposal | D12: 18165596 | E12: 0.5009 | F12: 46163 | G12: =IF(F12="","",TODAY()-F12) | H12: 46301 | I12: =IF(OR(B12="",D12=""),"",D12*VLOOKUP(B12,Lookup!$A$2:$B$5,2,FALSE)) | J12: =IF(OR(I12="",E12=""),"",I12*E12)
A13: Xander Aviation | B13: Treasury Mgmt | C13: Lead | D13: 101352.17 | E13: 0.0709 | F13: 46153 | G13: =IF(F13="","",TODAY()-F13) | H13: 46354 | I13: =IF(OR(B13="",D13=""),"",D13*VLOOKUP(B13,Lookup!$A$2:$B$5,2,FALSE)) | J13: =IF(OR(I13="",E13=""),"",I13*E13)
A14: Yellowstone Ranch | B14: Other Fees | C14: Lead | D14: 4379.97 | E14: 0.0802 | F14: 46120 | G14: =IF(F14="","",TODAY()-F14) | H14: 46354 | I14: =IF(OR(B14="",D14=""),"",D14*VLOOKUP(B14,Lookup!$A$2:$B$5,2,FALSE)) | J14: =IF(OR(I14="",E14=""),"",I14*E14)
... A16: Alamo Equipment | B16: Deposits | C16: Closed | D16: 1565237.5 | E16: 0.9879 | F16: 46148 | G16: =IF(F16="","",TODAY()-F16) | H16: 46224 | I16: =IF(OR(B16="",D16=""),"",D16*VLOOKUP(B16,Lookup!$A$2:$B$5,2,FALSE)) | J16: =IF(OR(I16="",E16=""),"",I16*E16)
E17: =IF(C17="","",VLOOKUP(C17,Lookup!$D$2:$E$6,2,FALSE)) | G17: =IF(F17="","",TODAY()-F17) | I17: =IF(OR(B17="",D17=""),"",D17*VLOOKUP(B17,Lookup!$A$2:$B$5,2,FALSE)) | J17: =IF(OR(I17="",E17=""),"",I17*E17)
E18: =IF(C18="","",VLOOKUP(C18,Lookup!$D$2:$E$6,2,FALSE)) | G18: =IF(F18="","",TODAY()-F18) | I18: =IF(OR(B18="",D18=""),"",D18*VLOOKUP(B18,Lookup!$A$2:$B$5,2,FALSE)) | J18: =IF(OR(I18="",E18=""),"",I18*E18)
E19: =IF(C19="","",VLOOKUP(C19,Lookup!$D$2:$E$6,2,FALSE)) | G19: =IF(F19="","",TODAY()-F19) | I19: =IF(OR(B19="",D19=""),"",D19*VLOOKUP(B19,Lookup!$A$2:$B$5,2,FALSE)) | J19: =IF(OR(I19="",E19=""),"",I19*E19)
E20: =IF(C20="","",VLOOKUP(C20,Lookup!$D$2:$E$6,2,FALSE)) | G20: =IF(F20="","",TODAY()-F20) | I20: =IF(OR(B20="",D20=""),"",D20*VLOOKUP(B20,Lookup!$A$2:$B$5,2,FALSE)) | J20: =IF(OR(I20="",E20=""),"",I20*E20)
E21: =IF(C21="","",VLOOKUP(C21,Lookup!$D$2:$E$6,2,FALSE)) | G21: =IF(F21="","",TODAY()-F21) | I21: =IF(OR(B21="",D21=""),"",D21*VLOOKUP(B21,Lookup!$A$2:$B$5,2,FALSE)) | J21: =IF(OR(I21="",E21=""),"",I21*E21)
E22: =IF(C22="","",VLOOKUP(C22,Lookup!$D$2:$E$6,2,FALSE)) | G22: =IF(F22="","",TODAY()-F22) | I22: =IF(OR(B22="",D22=""),"",D22*VLOOKUP(B22,Lookup!$A$2:$B$5,2,FALSE)) | J22: =IF(OR(I22="",E22=""),"",I22*E22)
E23: =IF(C23="","",VLOOKUP(C23,Lookup!$D$2:$E$6,2,FALSE)) | G23: =IF(F23="","",TODAY()-F23) | I23: =IF(OR(B23="",D23=""),"",D23*VLOOKUP(B23,Lookup!$A$2:$B$5,2,FALSE)) | J23: =IF(OR(I23="",E23=""),"",I23*E23)
E24: =IF(C24="","",VLOOKUP(C24,Lookup!$D$2:$E$6,2,FALSE)) | G24: =IF(F24="","",TODAY()-F24) | I24: =IF(OR(B24="",D24=""),"",D24*VLOOKUP(B24,Lookup!$A$2:$B$5,2,FALSE)) | J24: =IF(OR(I24="",E24=""),"",I24*E24)
E25: =IF(C25="","",VLOOKUP(C25,Lookup!$D$2:$E$6,2,FALSE)) | G25: =IF(F25="","",TODAY()-F25) | I25: =IF(OR(B25="",D25=""),"",D25*VLOOKUP(B25,Lookup!$A$2:$B$5,2,FALSE)) | J25: =IF(OR(I25="",E25=""),"",I25*E25)
E26: =IF(C26="","",VLOOKUP(C26,Lookup!$D$2:$E$6,2,FALSE)) | G26: =IF(F26="","",TODAY()-F26) | I26: =IF(OR(B26="",D26=""),"",D26*VLOOKUP(B26,Lookup!$A$2:$B$5,2,FALSE)) | J26: =IF(OR(I26="",E26=""),"",I26*E26)
E27: =IF(C27="","",VLOOKUP(C27,Lookup!$D$2:$E$6,2,FALSE)) | G27: =IF(F27="","",TODAY()-F27) | I27: =IF(OR(B27="",D27=""),"",D27*VLOOKUP(B27,Lookup!$A$2:$B$5,2,FALSE)) | J27: =IF(OR(I27="",E27=""),"",I27*E27)
E28: =IF(C28="","",VLOOKUP(C28,Lookup!$D$2:$E$6,2,FALSE)) | G28: =IF(F28="","",TODAY()-F28) | I28: =IF(OR(B28="",D28=""),"",D28*VLOOKUP(B28,Lookup!$A$2:$B$5,2,FALSE)) | J28: =IF(OR(I28="",E28=""),"",I28*E28)
... E32: =IF(C32="","",VLOOKUP(C32,Lookup!$D$2:$E$6,2,FALSE)) | G32: =IF(F32="","",TODAY()-F32) | I32: =IF(OR(B32="",D32=""),"",D32*VLOOKUP(B32,Lookup!$A$2:$B$5,2,FALSE)) | J32: =IF(OR(I32="",E32=""),"",I32*E32)

Sheet Lookup
A1: Product | B1: Spread | D1: Stage | E1: Probability | G1: RMs | H1: Market
A2: Comm Loan | B2: 0.034 | D2: Lead | E2: 0.1 | G2: M. Reyes | H2: Houston
A3: Deposits | B3: 0.005 | D3: Qualified | E3: 0.25 | G3: D. Patel | H3: Houston
A4: Treasury Mgmt | B4: 1 | D4: Proposal | E4: 0.5 | G4: A. Tran | H4: Houston
A5: Other Fees | B5: 1 | D5: Commit | E5: 0.8 | G5: K. Williams | H5: Houston
D6: Closed | E6: 1 | G6: R. Chen | H6: Dallas
G7: S. Garcia | H7: Dallas
G8: B. Foster | H8: Dallas
